SCons/Action.py
SCons/Builder.py
SCons/CacheDir.py
SCons/Conftest.py
SCons/Debug.py
SCons/Defaults.py
SCons/Environment.py
SCons/EnvironmentValues.py
SCons/EnvironmentValuesTest.py
SCons/Errors.py
SCons/Executor.py
SCons/Memoize.py
SCons/PathList.py
SCons/SConf.py
SCons/SConsign.py
SCons/Subst.py
SCons/Warnings.py
SCons/__init__.py
SCons/__main__.py
SCons/cpp.py
SCons/dblite.py
SCons/exitfuncs.py
SCons/Node/Alias.py
SCons/Node/FS.py
SCons/Node/Python.py
SCons/Node/__init__.py
SCons/Platform/__init__.py
SCons/Platform/aix.py
SCons/Platform/cygwin.py
SCons/Platform/darwin.py
SCons/Platform/hpux.py
SCons/Platform/irix.py
SCons/Platform/mingw.py
SCons/Platform/os2.py
SCons/Platform/posix.py
SCons/Platform/sunos.py
SCons/Platform/virtualenv.py
SCons/Platform/win32.py
SCons/Scanner/C.py
SCons/Scanner/D.py
SCons/Scanner/Dir.py
SCons/Scanner/Fortran.py
SCons/Scanner/IDL.py
SCons/Scanner/Java.py
SCons/Scanner/LaTeX.py
SCons/Scanner/Prog.py
SCons/Scanner/Python.py
SCons/Scanner/RC.py
SCons/Scanner/SWIG.py
SCons/Scanner/__init__.py
SCons/Script/Interactive.py
SCons/Script/Main.py
SCons/Script/SConsOptions.py
SCons/Script/SConscript.py
SCons/Script/__init__.py
SCons/Taskmaster/Job.py
SCons/Taskmaster/__init__.py
SCons/Tool/386asm.py
SCons/Tool/DCommon.py
SCons/Tool/FortranCommon.py
SCons/Tool/GettextCommon.py
SCons/Tool/JavaCommon.py
SCons/Tool/PharLapCommon.py
SCons/Tool/__init__.py
SCons/Tool/aixc++.py
SCons/Tool/aixcc.py
SCons/Tool/aixcxx.py
SCons/Tool/aixf77.py
SCons/Tool/aixlink.py
SCons/Tool/applelink.py
SCons/Tool/ar.py
SCons/Tool/as.py
SCons/Tool/asm.py
SCons/Tool/bcc32.py
SCons/Tool/c++.py
SCons/Tool/cc.py
SCons/Tool/clang.py
SCons/Tool/clangxx.py
SCons/Tool/compilation_db.py
SCons/Tool/cvf.py
SCons/Tool/cxx.py
SCons/Tool/cyglink.py
SCons/Tool/default.py
SCons/Tool/dmd.py
SCons/Tool/dvi.py
SCons/Tool/dvipdf.py
SCons/Tool/dvips.py
SCons/Tool/f03.py
SCons/Tool/f08.py
SCons/Tool/f77.py
SCons/Tool/f90.py
SCons/Tool/f95.py
SCons/Tool/filesystem.py
SCons/Tool/fortran.py
scons-4.10.0.dist-info/licenses/LICENSE
scons-4.10.0.dist-info/licenses/SCons/Tool/docbook/docbook-xsl-1.76.1/COPYING
scons-4.10.0.dist-info/METADATA
scons-4.10.0.dist-info/WHEEL
scons-4.10.0.dist-info/entry_points.txt
scons-4.10.0.dist-info/top_level.txt
scons-4.10.0.dist-info/RECORD
