Metadata-Version: 2.4
Name: SCons
Version: 4.10.0
Summary: Open Source next-generation build tool.
Author-email: William Deegan <bill@baddogconsulting.com>
License-Expression: MIT
Project-URL: Homepage, https://www.scons.org/
Project-URL: Documentation, https://scons.org/documentation.html
Project-URL: Twitter, https://twitter.com/SConsProject
Project-URL: GitHub, https://github.com/SCons/scons
Project-URL: Bug-Tracker, https://github.com/SCons/scons/issues
Project-URL: Discord, https://discord.gg/pejaFYrD9n
Project-URL: Mailing lists, https://scons.org/lists.html
Classifier: Development Status :: 5 - Production/Stable
Classifier: Topic :: Software Development :: Build Tools
Classifier: Programming Language :: Python
Classifier: Programming Language :: Python :: 3
Classifier: Programming Language :: Python :: 3 :: Only
Classifier: Programming Language :: Python :: 3.7
Classifier: Programming Language :: Python :: 3.8
Classifier: Programming Language :: Python :: 3.9
Classifier: Programming Language :: Python :: 3.10
Classifier: Programming Language :: Python :: 3.11
Classifier: Programming Language :: Python :: 3.12
Classifier: Programming Language :: Python :: 3.13
Classifier: Environment :: Console
Classifier: Intended Audience :: Developers
Classifier: Operating System :: POSIX :: Linux
Classifier: Operating System :: Unix
Classifier: Operating System :: MacOS
Classifier: Operating System :: Microsoft :: Windows
Requires-Python: >=3.7
License-File: LICENSE
License-File: SCons/Tool/docbook/docbook-xsl-1.76.1/COPYING
Provides-Extra: dev
Requires-Dist: ninja; extra == "dev"
Requires-Dist: psutil; extra == "dev"
Requires-Dist: lxml<5; (sys_platform != "win32" and python_version < "3.13") and extra == "dev"
Provides-Extra: pkg
Requires-Dist: ninja; extra == "pkg"
Requires-Dist: psutil; extra == "pkg"
Requires-Dist: readme-renderer; extra == "pkg"
Requires-Dist: sphinx; extra == "pkg"
Requires-Dist: sphinx-book-theme; extra == "pkg"
Requires-Dist: rst2pdf; extra == "pkg"
Requires-Dist: build; extra == "pkg"
Requires-Dist: twine; extra == "pkg"
Requires-Dist: packaging; extra == "pkg"
Dynamic: license-file
